pyfend-0.1.2.dist-info/METADATA
pyfend-0.1.2.dist-info/WHEEL
pyfend/__init__.py
pyfend/__init__.pyi
pyfend/py.typed
pyfend/pyfend.cpython-312-s390x-linux-gnu.so
pyfend-0.1.2.dist-info/RECORD
