Metadata-Version: 2.4
Name: pyfend
Version: 0.1.2
Classifier: Programming Language :: Rust
Requires-Dist: maturin
Summary: python bindings for fend-core
Requires-Python: >=3.7
